pymetard/__init__.py
pymetard/cli.py
pymetard/logger.py
pymetard/metar/__init__.py
pymetard/metar/downloader.py
pymetard/metar/meteo.py
pymetard/metar/station.py
pymetard/metar/stations.txt
tests/__init__.py
tests/pymetard/__init__.py
tests/pymetard/metar/__init__.py
tests/pymetard/metar/test_station.py
pymetard-0.0.4.dist-info/LICENSE
pymetard-0.0.4.dist-info/METADATA
pymetard-0.0.4.dist-info/WHEEL
pymetard-0.0.4.dist-info/entry_points.txt
pymetard-0.0.4.dist-info/top_level.txt
pymetard-0.0.4.dist-info/RECORD
